[
    {
        "id_num": 100007,
        "year": 2015,
        "discharges": 1424,
        "drg3": 871,
        "disc_times_pay": 15097248,
        "name": "FLORIDA HOSPITAL",
        "city": "ORLANDO",
        "state": "FL",
        "region": "FL - Orlando"
    },
    {
        "id_num": 50030,
        "year": 2015,
        "discharges": 1385,
        "drg3": 871,
        "disc_times_pay": 18215520,
        "name": "OROVILLE HOSPITAL",
        "city": "OROVILLE",
        "state": "CA",
        "region": "CA - Chico"
    },
    {
        "id_num": 50030,
        "year": 2014,
        "discharges": 1297,
        "drg3": 871,
        "disc_times_pay": 16898613,
        "name": "OROVILLE HOSPITAL",
        "city": "OROVILLE",
        "state": "CA",
        "region": "CA - Chico"
    },
    {
        "id_num": 220074,
        "year": 2015,
        "discharges": 1241,
        "drg3": 871,
        "disc_times_pay": 15514982,
        "name": "SOUTHCOAST HOSPITAL GROUP, INC",
        "city": "FALL RIVER",
        "state": "MA",
        "region": "MA - Boston"
    },
    {
        "id_num": 70022,
        "year": 2015,
        "discharges": 1233,
        "drg3": 871,
        "disc_times_pay": 20741526,
        "name": "YALE-NEW HAVEN HOSPITAL",
        "city": "NEW HAVEN",
        "state": "CT",
        "region": "CT - New Haven"
    },
    {
        "id_num": 450184,
        "year": 2015,
        "discharges": 1229,
        "drg3": 871,
        "disc_times_pay": 13087621,
        "name": "MEMORIAL HERMANN HOSPITAL SYSTEM",
        "city": "HOUSTON",
        "state": "TX",
        "region": "TX - Houston"
    },
    {
        "id_num": 340040,
        "year": 2015,
        "discharges": 1095,
        "drg3": 871,
        "disc_times_pay": 13158615,
        "name": "VIDANT MEDICAL CENTER",
        "city": "GREENVILLE",
        "state": "NC",
        "region": "NC - Greenville"
    },
    {
        "id_num": 450184,
        "year": 2014,
        "discharges": 1077,
        "drg3": 871,
        "disc_times_pay": 12075324,
        "name": "MEMORIAL HERMANN HOSPITAL SYSTEM",
        "city": "HOUSTON",
        "state": "TX",
        "region": "TX - Houston"
    },
    {
        "id_num": 440049,
        "year": 2015,
        "discharges": 1072,
        "drg3": 871,
        "disc_times_pay": 12262608,
        "name": "METHODIST HEALTHCARE MEMPHIS HOSPITALS",
        "city": "MEMPHIS",
        "state": "TN",
        "region": "TN - Memphis"
    },
    {
        "id_num": 50625,
        "year": 2015,
        "discharges": 1068,
        "drg3": 871,
        "disc_times_pay": 18607764,
        "name": "CEDARS-SINAI MEDICAL CENTER",
        "city": "LOS ANGELES",
        "state": "CA",
        "region": "CA - Los Angeles"
    },
    {
        "id_num": 170122,
        "year": 2015,
        "discharges": 1046,
        "drg3": 871,
        "disc_times_pay": 11055174,
        "name": "VIA CHRISTI HOSPITALS WICHITA, INC",
        "city": "WICHITA",
        "state": "KS",
        "region": "KS - Wichita"
    },
    {
        "id_num": 490021,
        "year": 2015,
        "discharges": 1029,
        "drg3": 871,
        "disc_times_pay": 10003938,
        "name": "CENTRA  HEALTH, INC",
        "city": "LYNCHBURG",
        "state": "VA",
        "region": "VA - Lynchburg"
    },
    {
        "id_num": 450054,
        "year": 2015,
        "discharges": 1028,
        "drg3": 871,
        "disc_times_pay": 11749012,
        "name": "SCOTT & WHITE MEDICAL CENTER - TEMPLE",
        "city": "TEMPLE",
        "state": "TX",
        "region": "TX - Temple"
    },
    {
        "id_num": 330055,
        "year": 2014,
        "discharges": 1010,
        "drg3": 871,
        "disc_times_pay": 16635710,
        "name": "NEW YORK HOSPITAL MEDICAL CENTER OF QUEENS",
        "city": "FLUSHING",
        "state": "NY",
        "region": "NY - East Long Island"
    },
    {
        "id_num": 80001,
        "year": 2015,
        "discharges": 992,
        "drg3": 871,
        "disc_times_pay": 12137120,
        "name": "CHRISTIANA CARE HEALTH SERVICES, INC.",
        "city": "NEWARK",
        "state": "DE",
        "region": "DE - Wilmington"
    },
    {
        "id_num": 330194,
        "year": 2014,
        "discharges": 979,
        "drg3": 871,
        "disc_times_pay": 19920692,
        "name": "MAIMONIDES MEDICAL CENTER",
        "city": "BROOKLYN",
        "state": "NY",
        "region": "NY - Manhattan"
    },
    {
        "id_num": 70022,
        "year": 2014,
        "discharges": 976,
        "drg3": 871,
        "disc_times_pay": 17761248,
        "name": "YALE-NEW HAVEN HOSPITAL",
        "city": "NEW HAVEN",
        "state": "CT",
        "region": "CT - New Haven"
    },
    {
        "id_num": 490021,
        "year": 2014,
        "discharges": 947,
        "drg3": 871,
        "disc_times_pay": 9499357,
        "name": "CENTRA  HEALTH, INC",
        "city": "LYNCHBURG",
        "state": "VA",
        "region": "VA - Lynchburg"
    },
    {
        "id_num": 220074,
        "year": 2014,
        "discharges": 945,
        "drg3": 871,
        "disc_times_pay": 11855025,
        "name": "SOUTHCOAST HOSPITAL GROUP, INC",
        "city": "FALL RIVER",
        "state": "MA",
        "region": "MA - Boston"
    },
    {
        "id_num": 330194,
        "year": 2015,
        "discharges": 945,
        "drg3": 871,
        "disc_times_pay": 18186525,
        "name": "MAIMONIDES MEDICAL CENTER",
        "city": "BROOKLYN",
        "state": "NY",
        "region": "NY - Manhattan"
    },
    {
        "id_num": 310015,
        "year": 2015,
        "discharges": 944,
        "drg3": 871,
        "disc_times_pay": 12329584,
        "name": "MORRISTOWN MEDICAL CENTER",
        "city": "MORRISTOWN",
        "state": "NJ",
        "region": "NJ - Morristown"
    },
    {
        "id_num": 330059,
        "year": 2013,
        "discharges": 941,
        "drg3": 871,
        "disc_times_pay": 20250320,
        "name": "MONTEFIORE MEDICAL CENTER",
        "city": "BRONX",
        "state": "NY",
        "region": "NY - Bronx"
    },
    {
        "id_num": 330106,
        "year": 2015,
        "discharges": 940,
        "drg3": 871,
        "disc_times_pay": 14484460,
        "name": "NORTH SHORE UNIVERSITY HOSPITAL",
        "city": "MANHASSET",
        "state": "NY",
        "region": "NY - East Long Island"
    },
    {
        "id_num": 310015,
        "year": 2014,
        "discharges": 931,
        "drg3": 871,
        "disc_times_pay": 12219375,
        "name": "MORRISTOWN MEDICAL CENTER",
        "city": "MORRISTOWN",
        "state": "NJ",
        "region": "NJ - Morristown"
    },
    {
        "id_num": 450388,
        "year": 2015,
        "discharges": 914,
        "drg3": 871,
        "disc_times_pay": 9480922,
        "name": "METHODIST HOSPITAL",
        "city": "SAN ANTONIO",
        "state": "TX",
        "region": "TX - San Antonio"
    },
    {
        "id_num": 440049,
        "year": 2014,
        "discharges": 914,
        "drg3": 871,
        "disc_times_pay": 10389438,
        "name": "METHODIST HEALTHCARE MEMPHIS HOSPITALS",
        "city": "MEMPHIS",
        "state": "TN",
        "region": "TN - Memphis"
    },
    {
        "id_num": 440002,
        "year": 2015,
        "discharges": 914,
        "drg3": 871,
        "disc_times_pay": 8755206,
        "name": "JACKSON-MADISON COUNTY GENERAL HOSPITAL",
        "city": "JACKSON",
        "state": "TN",
        "region": "TN - Jackson"
    },
    {
        "id_num": 330059,
        "year": 2015,
        "discharges": 909,
        "drg3": 871,
        "disc_times_pay": 18561780,
        "name": "MONTEFIORE MEDICAL CENTER",
        "city": "BRONX",
        "state": "NY",
        "region": "NY - Bronx"
    },
    {
        "id_num": 330059,
        "year": 2011,
        "discharges": 903,
        "drg3": 871,
        "disc_times_pay": 20430375,
        "name": "MONTEFIORE MEDICAL CENTER",
        "city": "BRONX",
        "state": "NY",
        "region": "NY - Bronx"
    },
    {
        "id_num": 440002,
        "year": 2014,
        "discharges": 903,
        "drg3": 871,
        "disc_times_pay": 8905386,
        "name": "JACKSON-MADISON COUNTY GENERAL HOSPITAL",
        "city": "JACKSON",
        "state": "TN",
        "region": "TN - Jackson"
    },
    {
        "id_num": 330101,
        "year": 2015,
        "discharges": 892,
        "drg3": 871,
        "disc_times_pay": 18740920,
        "name": "NEW YORK-PRESBYTERIAN HOSPITAL",
        "city": "NEW YORK",
        "state": "NY",
        "region": "NY - Manhattan"
    },
    {
        "id_num": 450184,
        "year": 2013,
        "discharges": 891,
        "drg3": 871,
        "disc_times_pay": 10458558,
        "name": "MEMORIAL HERMANN HOSPITAL SYSTEM",
        "city": "HOUSTON",
        "state": "TX",
        "region": "TX - Houston"
    },
    {
        "id_num": 450388,
        "year": 2011,
        "discharges": 889,
        "drg3": 871,
        "disc_times_pay": 10132822,
        "name": "METHODIST HOSPITAL",
        "city": "SAN ANTONIO",
        "state": "TX",
        "region": "TX - San Antonio"
    },
    {
        "id_num": 450388,
        "year": 2012,
        "discharges": 884,
        "drg3": 871,
        "disc_times_pay": 10224344,
        "name": "METHODIST HOSPITAL",
        "city": "SAN ANTONIO",
        "state": "TX",
        "region": "TX - San Antonio"
    },
    {
        "id_num": 370091,
        "year": 2015,
        "discharges": 883,
        "drg3": 871,
        "disc_times_pay": 8464438,
        "name": "SAINT FRANCIS HOSPITAL, INC",
        "city": "TULSA",
        "state": "OK",
        "region": "OK - Tulsa"
    },
    {
        "id_num": 340028,
        "year": 2015,
        "discharges": 866,
        "drg3": 871,
        "disc_times_pay": 8937120,
        "name": "CAPE FEAR VALLEY MEDICAL CENTER",
        "city": "FAYETTEVILLE",
        "state": "NC",
        "region": "NC - Raleigh"
    },
    {
        "id_num": 390046,
        "year": 2015,
        "discharges": 861,
        "drg3": 871,
        "disc_times_pay": 9518355,
        "name": "YORK HOSPITAL",
        "city": "YORK",
        "state": "PA",
        "region": "PA - York"
    },
    {
        "id_num": 330055,
        "year": 2013,
        "discharges": 857,
        "drg3": 871,
        "disc_times_pay": 14974361,
        "name": "NEW YORK HOSPITAL MEDICAL CENTER OF QUEENS",
        "city": "FLUSHING",
        "state": "NY",
        "region": "NY - East Long Island"
    },
    {
        "id_num": 450184,
        "year": 2012,
        "discharges": 857,
        "drg3": 871,
        "disc_times_pay": 10087747,
        "name": "MEMORIAL HERMANN HOSPITAL SYSTEM",
        "city": "HOUSTON",
        "state": "TX",
        "region": "TX - Houston"
    },
    {
        "id_num": 110029,
        "year": 2013,
        "discharges": 852,
        "drg3": 871,
        "disc_times_pay": 9091692,
        "name": "NORTHEAST GEORGIA MEDICAL CENTER, INC",
        "city": "GAINESVILLE",
        "state": "GA",
        "region": "GA - Atlanta"
    },
    {
        "id_num": 180088,
        "year": 2015,
        "discharges": 846,
        "drg3": 871,
        "disc_times_pay": 9127494,
        "name": "NORTON HOSPITAL/NORTON MEDICAL PAVILIONS/KOSAIR CH",
        "city": "LOUISVILLE",
        "state": "KY",
        "region": "KY - Louisville"
    },
    {
        "id_num": 340040,
        "year": 2014,
        "discharges": 840,
        "drg3": 871,
        "disc_times_pay": 10987200,
        "name": "VIDANT MEDICAL CENTER",
        "city": "GREENVILLE",
        "state": "NC",
        "region": "NC - Greenville"
    },
    {
        "id_num": 330059,
        "year": 2012,
        "discharges": 839,
        "drg3": 871,
        "disc_times_pay": 19620854,
        "name": "MONTEFIORE MEDICAL CENTER",
        "city": "BRONX",
        "state": "NY",
        "region": "NY - Bronx"
    },
    {
        "id_num": 450054,
        "year": 2014,
        "discharges": 839,
        "drg3": 871,
        "disc_times_pay": 9762604,
        "name": "SCOTT & WHITE MEMORIAL HOSPITAL",
        "city": "TEMPLE",
        "state": "TX",
        "region": "TX - Temple"
    },
    {
        "id_num": 330055,
        "year": 2015,
        "discharges": 838,
        "drg3": 871,
        "disc_times_pay": 13925046,
        "name": "NEW YORK-PRESBYTERIAN/QUEENS",
        "city": "FLUSHING",
        "state": "NY",
        "region": "NY - East Long Island"
    },
    {
        "id_num": 330106,
        "year": 2013,
        "discharges": 833,
        "drg3": 871,
        "disc_times_pay": 13098092,
        "name": "NORTH SHORE UNIVERSITY HOSPITAL",
        "city": "MANHASSET",
        "state": "NY",
        "region": "NY - East Long Island"
    },
    {
        "id_num": 230130,
        "year": 2015,
        "discharges": 829,
        "drg3": 871,
        "disc_times_pay": 9988621,
        "name": "BEAUMONT HOSPITAL, ROYAL OAK",
        "city": "ROYAL OAK",
        "state": "MI",
        "region": "MI - Royal Oak"
    },
    {
        "id_num": 50030,
        "year": 2013,
        "discharges": 829,
        "drg3": 871,
        "disc_times_pay": 11720402,
        "name": "OROVILLE HOSPITAL",
        "city": "OROVILLE",
        "state": "CA",
        "region": "CA - Chico"
    },
    {
        "id_num": 170122,
        "year": 2014,
        "discharges": 827,
        "drg3": 871,
        "disc_times_pay": 9115194,
        "name": "VIA CHRISTI HOSPITALS WICHITA, INC",
        "city": "WICHITA",
        "state": "KS",
        "region": "KS - Wichita"
    },
    {
        "id_num": 230141,
        "year": 2015,
        "discharges": 825,
        "drg3": 871,
        "disc_times_pay": 9631875,
        "name": "MCLAREN FLINT",
        "city": "FLINT",
        "state": "MI",
        "region": "MI - Flint"
    },
    {
        "id_num": 230195,
        "year": 2015,
        "discharges": 818,
        "drg3": 871,
        "disc_times_pay": 9050352,
        "name": "ST JOHN MACOMB-OAKLAND HOSPITAL-MACOMB CENTER",
        "city": "WARREN",
        "state": "MI",
        "region": "MI - Detroit"
    },
    {
        "id_num": 420078,
        "year": 2015,
        "discharges": 817,
        "drg3": 871,
        "disc_times_pay": 9479651,
        "name": "GHS GREENVILLE MEMORIAL HOSPITAL",
        "city": "GREENVILLE",
        "state": "SC",
        "region": "SC - Greenville"
    },
    {
        "id_num": 440049,
        "year": 2012,
        "discharges": 815,
        "drg3": 871,
        "disc_times_pay": 10022055,
        "name": "METHODIST HEALTHCARE MEMPHIS HOSPITALS",
        "city": "MEMPHIS",
        "state": "TN",
        "region": "TN - Memphis"
    },
    {
        "id_num": 330059,
        "year": 2014,
        "discharges": 813,
        "drg3": 871,
        "disc_times_pay": 17046984,
        "name": "MONTEFIORE MEDICAL CENTER",
        "city": "BRONX",
        "state": "NY",
        "region": "NY - Bronx"
    },
    {
        "id_num": 230038,
        "year": 2015,
        "discharges": 810,
        "drg3": 871,
        "disc_times_pay": 9082530,
        "name": "SPECTRUM HEALTH - BUTTERWORTH CAMPUS",
        "city": "GRAND RAPIDS",
        "state": "MI",
        "region": "MI - Grand Rapids"
    },
    {
        "id_num": 450054,
        "year": 2013,
        "discharges": 809,
        "drg3": 871,
        "disc_times_pay": 9712045,
        "name": "SCOTT & WHITE MEMORIAL HOSPITAL",
        "city": "TEMPLE",
        "state": "TX",
        "region": "TX - Temple"
    },
    {
        "id_num": 440049,
        "year": 2013,
        "discharges": 808,
        "drg3": 871,
        "disc_times_pay": 9593384,
        "name": "METHODIST HEALTHCARE MEMPHIS HOSPITALS",
        "city": "MEMPHIS",
        "state": "TN",
        "region": "TN - Memphis"
    },
    {
        "id_num": 110029,
        "year": 2014,
        "discharges": 807,
        "drg3": 871,
        "disc_times_pay": 8358906,
        "name": "NORTHEAST GEORGIA MEDICAL CENTER, INC",
        "city": "GAINESVILLE",
        "state": "GA",
        "region": "GA - Atlanta"
    },
    {
        "id_num": 450388,
        "year": 2014,
        "discharges": 802,
        "drg3": 871,
        "disc_times_pay": 8594232,
        "name": "METHODIST HOSPITAL",
        "city": "SAN ANTONIO",
        "state": "TX",
        "region": "TX - San Antonio"
    },
    {
        "id_num": 330194,
        "year": 2013,
        "discharges": 799,
        "drg3": 871,
        "disc_times_pay": 17468537,
        "name": "MAIMONIDES MEDICAL CENTER",
        "city": "BROOKLYN",
        "state": "NY",
        "region": "NY - Manhattan"
    },
    {
        "id_num": 340028,
        "year": 2013,
        "discharges": 795,
        "drg3": 871,
        "disc_times_pay": 9741135,
        "name": "CAPE FEAR VALLEY MEDICAL CENTER",
        "city": "FAYETTEVILLE",
        "state": "NC",
        "region": "NC - Raleigh"
    },
    {
        "id_num": 310086,
        "year": 2015,
        "discharges": 795,
        "drg3": 871,
        "disc_times_pay": 9890595,
        "name": "KENNEDY UNIVERSITY HOSPITAL - STRATFORD DIV",
        "city": "STRATFORD",
        "state": "NJ",
        "region": "NJ - Camden"
    },
    {
        "id_num": 50084,
        "year": 2015,
        "discharges": 791,
        "drg3": 871,
        "disc_times_pay": 13003249,
        "name": "ST JOSEPH'S MEDICAL CENTER OF STOCKTON",
        "city": "STOCKTON",
        "state": "CA",
        "region": "CA - Stockton"
    },
    {
        "id_num": 450388,
        "year": 2013,
        "discharges": 790,
        "drg3": 871,
        "disc_times_pay": 8999680,
        "name": "METHODIST HOSPITAL",
        "city": "SAN ANTONIO",
        "state": "TX",
        "region": "TX - San Antonio"
    },
    {
        "id_num": 330106,
        "year": 2014,
        "discharges": 787,
        "drg3": 871,
        "disc_times_pay": 12666765,
        "name": "NORTH SHORE UNIVERSITY HOSPITAL",
        "city": "MANHASSET",
        "state": "NY",
        "region": "NY - East Long Island"
    },
    {
        "id_num": 310019,
        "year": 2015,
        "discharges": 786,
        "drg3": 871,
        "disc_times_pay": 11991216,
        "name": "ST JOSEPH'S REGIONAL MEDICAL CENTER",
        "city": "PATERSON",
        "state": "NJ",
        "region": "NJ - Paterson"
    },
    {
        "id_num": 330101,
        "year": 2014,
        "discharges": 784,
        "drg3": 871,
        "disc_times_pay": 16946160,
        "name": "NEW YORK-PRESBYTERIAN HOSPITAL",
        "city": "NEW YORK",
        "state": "NY",
        "region": "NY - Manhattan"
    },
    {
        "id_num": 340028,
        "year": 2014,
        "discharges": 783,
        "drg3": 871,
        "disc_times_pay": 9100809,
        "name": "CAPE FEAR VALLEY MEDICAL CENTER",
        "city": "FAYETTEVILLE",
        "state": "NC",
        "region": "NC - Raleigh"
    },
    {
        "id_num": 110029,
        "year": 2015,
        "discharges": 779,
        "drg3": 871,
        "disc_times_pay": 7802464,
        "name": "NORTHEAST GEORGIA MEDICAL CENTER, INC",
        "city": "GAINESVILLE",
        "state": "GA",
        "region": "GA - Atlanta"
    },
    {
        "id_num": 230092,
        "year": 2014,
        "discharges": 778,
        "drg3": 871,
        "disc_times_pay": 8474754,
        "name": "ALLEGIANCE HEALTH",
        "city": "JACKSON",
        "state": "MI",
        "region": "MI - Ann Arbor"
    },
    {
        "id_num": 70022,
        "year": 2013,
        "discharges": 768,
        "drg3": 871,
        "disc_times_pay": 14773248,
        "name": "YALE-NEW HAVEN HOSPITAL",
        "city": "NEW HAVEN",
        "state": "CT",
        "region": "CT - New Haven"
    },
    {
        "id_num": 390044,
        "year": 2014,
        "discharges": 760,
        "drg3": 871,
        "disc_times_pay": 8353160,
        "name": "READING HOSPITAL",
        "city": "READING",
        "state": "PA",
        "region": "PA - Reading"
    },
    {
        "id_num": 230130,
        "year": 2014,
        "discharges": 758,
        "drg3": 871,
        "disc_times_pay": 9266550,
        "name": "BEAUMONT HOSPITAL, ROYAL OAK",
        "city": "ROYAL OAK",
        "state": "MI",
        "region": "MI - Royal Oak"
    },
    {
        "id_num": 250004,
        "year": 2014,
        "discharges": 757,
        "drg3": 871,
        "disc_times_pay": 7815268,
        "name": "NORTH MISSISSIPPI MEDICAL CENTER",
        "city": "TUPELO",
        "state": "MS",
        "region": "MS - Tupelo"
    },
    {
        "id_num": 330106,
        "year": 2012,
        "discharges": 756,
        "drg3": 871,
        "disc_times_pay": 12911724,
        "name": "NORTH SHORE UNIVERSITY HOSPITAL",
        "city": "MANHASSET",
        "state": "NY",
        "region": "NY - East Long Island"
    },
    {
        "id_num": 320021,
        "year": 2015,
        "discharges": 755,
        "drg3": 871,
        "disc_times_pay": 7898810,
        "name": "PRESBYTERIAN HOSPITAL",
        "city": "ALBUQUERQUE",
        "state": "NM",
        "region": "NM - Albuquerque"
    },
    {
        "id_num": 450184,
        "year": 2011,
        "discharges": 754,
        "drg3": 871,
        "disc_times_pay": 8826324,
        "name": "MEMORIAL HERMANN HOSPITAL SYSTEM",
        "city": "HOUSTON",
        "state": "TX",
        "region": "TX - Houston"
    },
    {
        "id_num": 110029,
        "year": 2012,
        "discharges": 753,
        "drg3": 871,
        "disc_times_pay": 7901229,
        "name": "NORTHEAST GEORGIA MEDICAL CENTER, INC",
        "city": "GAINESVILLE",
        "state": "GA",
        "region": "GA - Atlanta"
    },
    {
        "id_num": 330126,
        "year": 2015,
        "discharges": 751,
        "drg3": 871,
        "disc_times_pay": 11626231,
        "name": "ORANGE REGIONAL MEDICAL CENTER",
        "city": "MIDDLETOWN",
        "state": "NY",
        "region": "NY - White Plains"
    },
    {
        "id_num": 50224,
        "year": 2015,
        "discharges": 747,
        "drg3": 871,
        "disc_times_pay": 8554644,
        "name": "HOAG MEMORIAL HOSPITAL PRESBYTERIAN",
        "city": "NEWPORT BEACH",
        "state": "CA",
        "region": "CA - Orange County"
    },
    {
        "id_num": 440048,
        "year": 2015,
        "discharges": 746,
        "drg3": 871,
        "disc_times_pay": 7791224,
        "name": "BAPTIST MEMORIAL HOSPITAL",
        "city": "MEMPHIS",
        "state": "TN",
        "region": "TN - Memphis"
    },
    {
        "id_num": 140067,
        "year": 2015,
        "discharges": 741,
        "drg3": 871,
        "disc_times_pay": 8252517,
        "name": "SAINT FRANCIS MEDICAL CENTER",
        "city": "PEORIA",
        "state": "IL",
        "region": "IL - Peoria"
    },
    {
        "id_num": 230070,
        "year": 2015,
        "discharges": 738,
        "drg3": 871,
        "disc_times_pay": 7603614,
        "name": "COVENANT MEDICAL CENTER",
        "city": "SAGINAW",
        "state": "MI",
        "region": "MI - Saginaw"
    },
    {
        "id_num": 230130,
        "year": 2011,
        "discharges": 736,
        "drg3": 871,
        "disc_times_pay": 10186240,
        "name": "WILLIAM BEAUMONT HOSPITAL",
        "city": "ROYAL OAK",
        "state": "MI",
        "region": "MI - Royal Oak"
    },
    {
        "id_num": 340091,
        "year": 2015,
        "discharges": 734,
        "drg3": 871,
        "disc_times_pay": 7246782,
        "name": "MOSES H CONE MEMORIAL HOSPITAL, THE",
        "city": "GREENSBORO",
        "state": "NC",
        "region": "NC - Greensboro"
    },
    {
        "id_num": 100007,
        "year": 2013,
        "discharges": 732,
        "drg3": 871,
        "disc_times_pay": 8327964,
        "name": "FLORIDA HOSPITAL",
        "city": "ORLANDO",
        "state": "FL",
        "region": "FL - Orlando"
    },
    {
        "id_num": 290001,
        "year": 2015,
        "discharges": 731,
        "drg3": 871,
        "disc_times_pay": 8508109,
        "name": "RENOWN REGIONAL MEDICAL CENTER",
        "city": "RENO",
        "state": "NV",
        "region": "NV - Reno"
    },
    {
        "id_num": 370091,
        "year": 2014,
        "discharges": 730,
        "drg3": 871,
        "disc_times_pay": 7381030,
        "name": "SAINT FRANCIS HOSPITAL, INC",
        "city": "TULSA",
        "state": "OK",
        "region": "OK - Tulsa"
    },
    {
        "id_num": 220100,
        "year": 2015,
        "discharges": 729,
        "drg3": 871,
        "disc_times_pay": 8721756,
        "name": "SOUTH SHORE HOSPITAL",
        "city": "SOUTH WEYMOUTH",
        "state": "MA",
        "region": "MA - Boston"
    },
    {
        "id_num": 230195,
        "year": 2014,
        "discharges": 726,
        "drg3": 871,
        "disc_times_pay": 8221224,
        "name": "ST JOHN MACOMB-OAKLAND HOSPITAL-MACOMB CENTER",
        "city": "WARREN",
        "state": "MI",
        "region": "MI - Detroit"
    },
    {
        "id_num": 450054,
        "year": 2012,
        "discharges": 723,
        "drg3": 871,
        "disc_times_pay": 9264522,
        "name": "SCOTT & WHITE MEMORIAL HOSPITAL",
        "city": "TEMPLE",
        "state": "TX",
        "region": "TX - Temple"
    },
    {
        "id_num": 230130,
        "year": 2012,
        "discharges": 721,
        "drg3": 871,
        "disc_times_pay": 10047856,
        "name": "BEAUMONT HEALTH SYSTEM",
        "city": "ROYAL OAK",
        "state": "MI",
        "region": "MI - Royal Oak"
    },
    {
        "id_num": 150162,
        "year": 2015,
        "discharges": 720,
        "drg3": 871,
        "disc_times_pay": 7448400,
        "name": "FRANCISCAN ST FRANCIS HEALTH - INDIANAPOLIS",
        "city": "INDIANAPOLIS",
        "state": "IN",
        "region": "IN - Indianapolis"
    },
    {
        "id_num": 230195,
        "year": 2013,
        "discharges": 719,
        "drg3": 871,
        "disc_times_pay": 8428837,
        "name": "ST JOHN MACOMB-OAKLAND HOSPITAL-MACOMB CENTER",
        "city": "WARREN",
        "state": "MI",
        "region": "MI - Detroit"
    },
    {
        "id_num": 340028,
        "year": 2011,
        "discharges": 717,
        "drg3": 871,
        "disc_times_pay": 9443607,
        "name": "CAPE FEAR VALLEY MEDICAL CENTER",
        "city": "FAYETTEVILLE",
        "state": "NC",
        "region": "NC - Raleigh"
    },
    {
        "id_num": 170122,
        "year": 2013,
        "discharges": 717,
        "drg3": 871,
        "disc_times_pay": 8196027,
        "name": "VIA CHRISTI HOSPITALS WICHITA INC",
        "city": "WICHITA",
        "state": "KS",
        "region": "KS - Wichita"
    },
    {
        "id_num": 230038,
        "year": 2014,
        "discharges": 715,
        "drg3": 871,
        "disc_times_pay": 8705840,
        "name": "SPECTRUM HEALTH - BUTTERWORTH CAMPUS",
        "city": "GRAND RAPIDS",
        "state": "MI",
        "region": "MI - Grand Rapids"
    },
    {
        "id_num": 100007,
        "year": 2014,
        "discharges": 715,
        "drg3": 871,
        "disc_times_pay": 8051615,
        "name": "FLORIDA HOSPITAL",
        "city": "ORLANDO",
        "state": "FL",
        "region": "FL - Orlando"
    },
    {
        "id_num": 340141,
        "year": 2015,
        "discharges": 713,
        "drg3": 871,
        "disc_times_pay": 8237289,
        "name": "NEW HANOVER REGIONAL MEDICAL CENTER",
        "city": "WILMINGTON",
        "state": "NC",
        "region": "NC - Wilmington"
    },
    {
        "id_num": 220012,
        "year": 2015,
        "discharges": 712,
        "drg3": 871,
        "disc_times_pay": 10362448,
        "name": "CAPE COD HOSPITAL",
        "city": "HYANNIS",
        "state": "MA",
        "region": "MA - Boston"
    },
    {
        "id_num": 230092,
        "year": 2015,
        "discharges": 711,
        "drg3": 871,
        "disc_times_pay": 7604145,
        "name": "ALLEGIANCE HEALTH",
        "city": "JACKSON",
        "state": "MI",
        "region": "MI - Ann Arbor"
    }
]